tvod/__init__.py
tvod-2.0.1.dist-info/LICENSE
tvod-2.0.1.dist-info/METADATA
tvod-2.0.1.dist-info/WHEEL
tvod-2.0.1.dist-info/entry_points.txt
tvod-2.0.1.dist-info/RECORD
