Metadata-Version: 2.1
Name: tvod
Version: 2.0.1
Summary: A package to retrieve Twitch VOD
Home-page: https://gitlab.com/jjocram/twitch-vod
License: GPL-3.0-or-later
Author: Marco Ferrati
Author-email: marco.ferrati@protonmail.com
Requires-Python: >=3.10,<4.0
Classifier: License :: OSI Approved :: GNU General Public License v3 or later (GPLv3+)
Classifier: License :: OSI Approved :: MIT License
Classifier: Operating System :: OS Independent
Classifier: Programming Language :: Python :: 3
Classifier: Programming Language :: Python :: 3.10
Classifier: Programming Language :: Python :: 3.11
Classifier: Programming Language :: Python :: 3
Requires-Dist: requests (>=2.28.0,<3.0.0)
Project-URL: Bug Tracker, https://gitlab.com/jjocram/twitch-vod/-/issues
Project-URL: Repository, https://gitlab.com/jjocram/twitch-vod
